{
  "ABLine": {
    "isHeadingSameWay": true,
    "distanceFromCurrentLinePivot": 0,
    "rEastAB": 0,
    "rNorthAB": 0,
    "A": {
      "northing": 0.015, 
      "easting": 0.001
    },
    "B": {
      "northing": 13.564674548957216,
      "easting": 1.1899409146465938 
    }
  },
  "guidanceLookPos": {
    "easting": 1.5,
    "northing": 1.1
  },
  "guidanceLineDistanceOff": 0,
  "guidanceLineSteerAngle": 0,
  "vehicle": {
    "stanleyHeadingErrorGain": 1,
    "stanleyDistanceErrorGain": 1,
    "stanleyIntegralGainAB": 1,
    "maxSteerAngle": 45
  },
  "tool": {
    "toolOffset": 0,
    "toolWidth": 50,
    "toolOverlap": 5
  },
  "yt": {
    "dxAB": 0,
	"dyAB": 0
  },
  "ahrs": {
    "imuRoll": 88888
  },
  "startSpeed": 1,
  "avgSpeed": 3,
  "isReverse": false
}
